slim_mcp/__init__.py
slim_mcp/client.py
slim_mcp/common.py
slim_mcp/helpers.py
slim_mcp/server.py
slim_mcp/examples/llamaindex_time_agent/README.md
slim_mcp/examples/llamaindex_time_agent/__init__.py
slim_mcp/examples/llamaindex_time_agent/main.py
slim_mcp/examples/mcp_server_time/README.md
slim_mcp/examples/mcp_server_time/__init__.py
slim_mcp/examples/mcp_server_time/server.py
slim_mcp-0.1.8.dist-info/METADATA
slim_mcp-0.1.8.dist-info/WHEEL
slim_mcp-0.1.8.dist-info/entry_points.txt
slim_mcp-0.1.8.dist-info/licenses/LICENSE
slim_mcp-0.1.8.dist-info/RECORD
