Metadata-Version: 2.4
Name: slim-mcp
Version: 0.1.8
Summary: Model Context Protocol with SLIM as transport
License-Expression: Apache-2.0
License-File: LICENSE
Classifier: Development Status :: 3 - Alpha
Classifier: Intended Audience :: Developers
Classifier: Programming Language :: Python :: 3.10
Classifier: Programming Language :: Python :: 3.11
Classifier: Programming Language :: Python :: 3.12
Classifier: Programming Language :: Python :: 3.13
Classifier: Topic :: Software Development :: Libraries
Requires-Python: <4.0,>=3.11
Requires-Dist: anyio>=4.5
Requires-Dist: mcp==1.6.0
Requires-Dist: slim-bindings>=0.7.1
